ezbullet/__init__.py
ezbullet/camera.py
ezbullet/data.py
ezbullet/geometry.py
ezbullet/shape.py
ezbullet/urdf.py
ezbullet/utils.py
ezbullet/world.py
ezbullet-0.1.2.dist-info/METADATA
ezbullet-0.1.2.dist-info/WHEEL
ezbullet-0.1.2.dist-info/RECORD
