Metadata-Version: 2.4
Name: ezbullet
Version: 0.1.2
Summary: Add your description here
Requires-Python: >=3.9
Requires-Dist: attrs>=25.3.0
Requires-Dist: ezpose>=0.1.9
Requires-Dist: ipykernel>=6.29.5
Requires-Dist: pybullet>=3.2.7
Requires-Dist: trimesh>=4.6.5
